easy_predictor/__init__.py
easy_predictor/classification.py
easy_predictor/linear.py
easy_predictor/stats.py
easy_predictor/table.py
easy_predictor-0.6.7.dist-info/LICENSE
easy_predictor-0.6.7.dist-info/METADATA
easy_predictor-0.6.7.dist-info/WHEEL
easy_predictor-0.6.7.dist-info/top_level.txt
easy_predictor-0.6.7.dist-info/RECORD
