Metadata-Version: 2.1
Name: easy-predictor
Version: 0.6.7
Summary: Perform regression/classification prediction on Excel dataset
Home-page: https://github.com/Tho100/easy_predictor
Author: Hafiy Danish
Author-email: nfrealyt@gmail.com
Classifier: Programming Language :: Python :: 3
Classifier: License :: OSI Approved :: MIT License
Classifier: Operating System :: OS Independent
Requires-Python: >=3.6
License-File: LICENSE
